humanize_ai_text/__init__.py
humanize_ai_text/client.py
humanize_ai_text-1.0.0.dist-info/METADATA
humanize_ai_text-1.0.0.dist-info/WHEEL
humanize_ai_text-1.0.0.dist-info/top_level.txt
humanize_ai_text-1.0.0.dist-info/RECORD
